cmadison/__init__.py
cmadison/cmadison.py
cmadison-0.5.1.dist-info/METADATA
cmadison-0.5.1.dist-info/RECORD
cmadison-0.5.1.dist-info/WHEEL
cmadison-0.5.1.dist-info/entry_points.txt
cmadison-0.5.1.dist-info/top_level.txt
