Metadata-Version: 2.1
Name: cmadison
Version: 0.5.1
Summary: A wrapper for rmadison including basic support for Ubuntu Cloud Archive
Home-page: http://github.com/wolsen/cmadison
Author: Billy Olsen
Author-email: billy.olsen@gmail.com
License: UNKNOWN
Platform: UNKNOWN
Classifier: Development Status :: 5 - Production/Stable
Classifier: Environment :: Console
Classifier: License :: OSI Approved :: GNU General Public License v3 (GPLv3)
Requires-Dist: lxml
Requires-Dist: requests
Requires-Dist: requests-cache
Requires-Dist: requestsexceptions
Requires-Dist: six
